synrxn/__init__.py
synrxn/build_manifest.py
synrxn/verify_manifest.py
synrxn/baseline/__init__.py
synrxn/baseline/classification.py
synrxn/baseline/property.py
synrxn/cluster/__init__.py
synrxn/cluster/butina.py
synrxn/cluster/ecfp.py
synrxn/cluster/wlfp.py
synrxn/data/__init__.py
synrxn/data/constants.py
synrxn/data/data_loader.py
synrxn/data/github_client.py
synrxn/data/utils.py
synrxn/data/zenodo_client.py
synrxn/io/__init__.py
synrxn/io/io.py
synrxn/metrics/__init__.py
synrxn/metrics/synthesis.py
synrxn/metrics/template.py
synrxn/split/__init__.py
synrxn/split/repeated_group_aware_kfold.py
synrxn/split/repeated_kfold.py
synrxn/statistics/__init__.py
synrxn/statistics/assumptions.py
synrxn/statistics/common.py
synrxn/statistics/nonparametric.py
synrxn/statistics/parametric.py
synrxn/statistics/runner.py
synrxn-0.0.7.dist-info/METADATA
synrxn-0.0.7.dist-info/WHEEL
synrxn-0.0.7.dist-info/licenses/LICENSE
synrxn-0.0.7.dist-info/RECORD
