Metadata-Version: 2.4
Name: synrxn
Version: 0.0.7
Summary: Reaction Database for benchmarking
Project-URL: homepage, https://github.com/TieuLongPhan/synrxn
Project-URL: source, https://github.com/TieuLongPhan/synrxn
Project-URL: issues, https://github.com/TieuLongPhan/synrxn/issues
Project-URL: documentation, https://synrxn.readthedocs.io/en/latest/
Author-email: Tieu Long Phan <tieu@bioinf.uni-leipzig.de>
License-File: LICENSE
Classifier: License :: OSI Approved :: MIT License
Classifier: Operating System :: OS Independent
Classifier: Programming Language :: Python :: 3
Requires-Python: >=3.11
Requires-Dist: openpyxl>=3.1.5
Requires-Dist: scikit-learn>=1.7.2
Requires-Dist: synkit>=1.0.1
Provides-Extra: all
Requires-Dist: numpy>=2.2.0; extra == 'all'
Requires-Dist: pandas>=1.5.3; extra == 'all'
Requires-Dist: scikit-posthocs>=0.11.4; extra == 'all'
Requires-Dist: scipy>=1.16.2; extra == 'all'
Requires-Dist: seaborn>=0.13.0; extra == 'all'
Provides-Extra: docs
Requires-Dist: sphinx-rtd-theme; extra == 'docs'
Requires-Dist: sphinx>=6.0; extra == 'docs'
Requires-Dist: sphinxcontrib-bibtex; extra == 'docs'
